MANIFEST.in
README.rst
requirements.stable.txt
requirements.txt
setup.py
tasks.py
lino_care/__init__.py
lino_care/setup_info.py
lino_care.egg-info/PKG-INFO
lino_care.egg-info/SOURCES.txt
lino_care.egg-info/dependency_links.txt
lino_care.egg-info/not-zip-safe
lino_care.egg-info/requires.txt
lino_care.egg-info/top_level.txt
lino_care/lib/__init__.py
lino_care/lib/cal/__init__.py
lino_care/lib/cal/models.py
lino_care/lib/cal/fixtures/__init__.py
lino_care/lib/cal/fixtures/std.py
lino_care/lib/care/__init__.py
lino_care/lib/care/help_texts.py
lino_care/lib/care/layouts.py
lino_care/lib/care/migrate.py
lino_care/lib/care/models.py
lino_care/lib/care/settings.py
lino_care/lib/care/user_types.py
lino_care/lib/care/workflows.py
lino_care/lib/care/fixtures/__init__.py
lino_care/lib/care/fixtures/demo.py
lino_care/lib/care/fixtures/linotickets.py
lino_care/lib/care/locale/de/LC_MESSAGES/django.mo
lino_care/lib/care/locale/de/LC_MESSAGES/django.po
lino_care/lib/care/locale/et/LC_MESSAGES/django.mo
lino_care/lib/care/locale/et/LC_MESSAGES/django.po
lino_care/lib/care/locale/fr/LC_MESSAGES/django.mo
lino_care/lib/care/locale/fr/LC_MESSAGES/django.po
lino_care/lib/contacts/__init__.py
lino_care/lib/contacts/models.py
lino_care/lib/contacts/fixtures/__init__.py
lino_care/lib/contacts/fixtures/demo.py
lino_care/lib/contacts/fixtures/std.py
lino_care/lib/courses/__init__.py
lino_care/lib/courses/desktop.py
lino_care/lib/courses/models.py
lino_care/lib/public/__init__.py
lino_care/lib/public/renderer.py
lino_care/lib/public/views.py
lino_care/lib/public/config/noi/index.html
lino_care/lib/public/config/noi/tickets.Ticket.html
lino_care/lib/tickets/__init__.py
lino_care/lib/tickets/models.py
lino_care/lib/tickets/workflows.py
lino_care/lib/topics/__init__.py
lino_care/lib/topics/models.py
lino_care/lib/users/__init__.py
lino_care/lib/users/desktop.py
lino_care/lib/users/models.py
lino_care/lib/users/fixtures/__init__.py
lino_care/lib/users/fixtures/demo.py
lino_care/lib/users/fixtures/demo2.py
lino_care/lib/users/fixtures/demo_users.py
tests/__init__.py