Metadata-Version: 1.1
Name: lino-care
Version: 20.1.0
Summary: A database for managing a network of helpers.
Home-page: http://care.lino-framework.org
Author: Luc Saffre
Author-email: luc@lino-framework.org
License: BSD-2-Clause
Platform: UNKNOWN
Classifier: Programming Language :: Python
Classifier: Programming Language :: Python :: 2
Classifier: Development Status :: 4 - Beta
Classifier: Environment :: Web Environment
Classifier: Framework :: Django
Classifier: Intended Audience :: Developers
Classifier: Intended Audience :: System Administrators
Classifier: Intended Audience :: Information Technology
Classifier: Intended Audience :: Customer Service
Classifier: License :: OSI Approved :: BSD License
Classifier: Operating System :: OS Independent
Classifier: Topic :: Software Development :: Bug Tracking
